llm_embed_jina.py
llm_embed_jina-0.1.2.dist-info/LICENSE
llm_embed_jina-0.1.2.dist-info/METADATA
llm_embed_jina-0.1.2.dist-info/WHEEL
llm_embed_jina-0.1.2.dist-info/entry_points.txt
llm_embed_jina-0.1.2.dist-info/top_level.txt
llm_embed_jina-0.1.2.dist-info/RECORD
