Metadata-Version: 2.1
Name: llm-embed-jina
Version: 0.1.2
Summary: Embedding models from Jina AI
Author: Simon Willison
License: Apache-2.0
Project-URL: Homepage, https://github.com/simonw/llm-embed-jina
Project-URL: Changelog, https://github.com/simonw/llm-embed-jina/releases
Project-URL: Issues, https://github.com/simonw/llm-embed-jina/issues
Project-URL: CI, https://github.com/simonw/llm-embed-jina/actions
Classifier: License :: OSI Approved :: Apache Software License
License-File: LICENSE
Requires-Dist: llm
Requires-Dist: transformers
Requires-Dist: torch
Provides-Extra: test
Requires-Dist: pytest ; extra == 'test'
